quackpass/__init__.py
quackpass/quackpass.py
quackpass-1.0.0.dist-info/METADATA
quackpass-1.0.0.dist-info/WHEEL
quackpass-1.0.0.dist-info/top_level.txt
quackpass-1.0.0.dist-info/RECORD
