Metadata-Version: 2.1
Name: quackpass
Version: 1.0.0
Summary: A simple password login for text based games.
Home-page: https://github.com
Author: Jonathan Calhoon
Author-email: youcannotcontactmethroughthis@gmail.com
License: UNKNOWN
Project-URL: Bug Tracker, https://github.com
Platform: UNKNOWN
Classifier: Programming Language :: Python :: 3
Classifier: License :: OSI Approved :: MIT License
Classifier: Operating System :: OS Independent
Requires-Python: >=3.6
